gaesd/__init__.py
gaesd/__version__.py
gaesd/sdk.py
gaesd/core/__init__.py
gaesd/core/decorators.py
gaesd/core/helpers.py
gaesd/core/span.py
gaesd/core/trace.py
gaesd/core/utils.py
gaesd/core/dispatchers/__init__.py
gaesd/core/dispatchers/dispatcher.py
gaesd/core/dispatchers/google_api_client_dispatcher.py
gaesd/core/dispatchers/rest_dispatcher.py
gaesd-0.7.2.dist-info/DESCRIPTION.rst
gaesd-0.7.2.dist-info/METADATA
gaesd-0.7.2.dist-info/RECORD
gaesd-0.7.2.dist-info/WHEEL
gaesd-0.7.2.dist-info/metadata.json
gaesd-0.7.2.dist-info/top_level.txt
